LICENSE
MANIFEST.in
README.rst
setup.py
allen/__init__.py
allen/addon_classes.py
allen/allenclient.py
allen/command_line.py
allen/exam.py
allen/exceptions.py
allen/solution.py
allen/test_record.py
allen/utils.py
allen/video.py
allen_py_client.egg-info/PKG-INFO
allen_py_client.egg-info/SOURCES.txt
allen_py_client.egg-info/dependency_links.txt
allen_py_client.egg-info/entry_points.txt
allen_py_client.egg-info/requires.txt
allen_py_client.egg-info/top_level.txt
test/__init__.py
test/test_client.py