Metadata-Version: 2.1
Name: allen-py-client
Version: 1.2.1
Summary: Unofficial python wrapper for Allen's web API.
Home-page: https://github.com/lamergameryt/allen-py-client
Author: Harsh Patil
Author-email: ifung230@gmail.com
License: UNKNOWN
Download-URL: https://github.com/lamergameryt/allen-py-client
Keywords: python,allen
Platform: UNKNOWN
Classifier: Intended Audience :: Developers
Classifier: License :: OSI Approved :: GNU General Public License v3 (GPLv3)
Classifier: Operating System :: OS Independent
Classifier: Programming Language :: Python
Classifier: Programming Language :: Python :: 3
Classifier: Programming Language :: Python :: 3.6
Classifier: Programming Language :: Python :: 3.7
Classifier: Programming Language :: Python :: 3.8
Classifier: Programming Language :: Python :: 3.9
License-File: LICENSE
